gallery_dl_server/__init__.py
gallery_dl_server/__main__.py
gallery_dl_server/app.py
gallery_dl_server/config.py
gallery_dl_server/download.py
gallery_dl_server/options.py
gallery_dl_server/output.py
gallery_dl_server/server.py
gallery_dl_server/utils.py
gallery_dl_server/version.py
gallery_dl_server/static/icons/about.txt
gallery_dl_server/static/icons/android-chrome-192x192.png
gallery_dl_server/static/icons/android-chrome-512x512.png
gallery_dl_server/static/icons/apple-touch-icon.png
gallery_dl_server/static/icons/favicon-16x16.png
gallery_dl_server/static/icons/favicon-32x32.png
gallery_dl_server/static/icons/favicon.ico
gallery_dl_server/static/icons/site.webmanifest
gallery_dl_server/static/scripts/index.js
gallery_dl_server/static/scripts/logs.js
gallery_dl_server/static/styles/common.css
gallery_dl_server/static/styles/index-dark.css
gallery_dl_server/static/styles/index.css
gallery_dl_server/static/styles/logs.css
gallery_dl_server/templates/index.html
gallery_dl_server/templates/logs.html
gallery_dl_server-0.8.1.dist-info/licenses/LICENSE
gallery_dl_server-0.8.1.dist-info/METADATA
gallery_dl_server-0.8.1.dist-info/WHEEL
gallery_dl_server-0.8.1.dist-info/entry_points.txt
gallery_dl_server-0.8.1.dist-info/top_level.txt
gallery_dl_server-0.8.1.dist-info/RECORD
