Metadata-Version: 2.4
Name: gallery-dl-server
Version: 0.8.1
Summary: Web UI for downloading media with gallery-dl and yt-dlp.
Author-email: qx6ghqkz <qx6ghqkz@proton.me>
Maintainer-email: qx6ghqkz <qx6ghqkz@proton.me>
License: The MIT License (MIT)
Project-URL: Documentation, https://github.com/qx6ghqkz/gallery-dl-server#readme
Project-URL: Repository, https://github.com/qx6ghqkz/gallery-dl-server
Project-URL: Issues, https://github.com/qx6ghqkz/gallery-dl-server/issues
Project-URL: Releases, https://github.com/qx6ghqkz/gallery-dl-server/releases
Project-URL: Docker, https://hub.docker.com/r/qx6ghqkz/gallery-dl-server
Keywords: image,gallery,video,media,downloader,server,web-ui,self-hosted,gallery-dl,youtube,yt-dlp
Classifier: Development Status :: 4 - Beta
Classifier: Environment :: Console
Classifier: Framework :: FastAPI
Classifier: Intended Audience :: End Users/Desktop
Classifier: License :: OSI Approved :: MIT License
Classifier: Natural Language :: English
Classifier: Operating System :: Microsoft :: Windows
Classifier: Operating System :: POSIX :: Linux
Classifier: Programming Language :: Python
Classifier: Programming Language :: Python :: 3
Classifier: Programming Language :: Python :: 3.10
Classifier: Programming Language :: Python :: 3.11
Classifier: Programming Language :: Python :: 3.12
Classifier: Programming Language :: Python :: 3.13
Classifier: Programming Language :: Python :: Implementation :: CPython
Classifier: Programming Language :: Python :: Implementation :: PyPy
Classifier: Topic :: Internet :: WWW/HTTP
Classifier: Topic :: Internet :: WWW/HTTP :: Dynamic Content
Classifier: Topic :: Internet :: WWW/HTTP :: HTTP Servers
Classifier: Topic :: Multimedia :: Graphics
Classifier: Topic :: Multimedia :: Sound/Audio
Classifier: Topic :: Multimedia :: Video
Classifier: Topic :: Utilities
Requires-Python: >=3.10
License-File: LICENSE
Requires-Dist: aiofiles>=24.1.0
Requires-Dist: gallery_dl<2.0.0,>=1.28.1
Requires-Dist: jinja2<4.0.0,>=3.1.5
Requires-Dist: python-multipart>=0.0.20
Requires-Dist: requests<3.0.0,>=2.32.3
Requires-Dist: starlette<1.0.0,>=0.45.1
Requires-Dist: uvicorn<1.0.0,>=0.32.0; (platform_machine != "x86_64" and platform_machine != "AMD64") or implementation_name != "cpython"
Requires-Dist: uvicorn[standard]<1.0.0,>=0.32.0; (platform_machine == "x86_64" or platform_machine == "AMD64") and implementation_name == "cpython"
Requires-Dist: watchfiles<2.0.0,>=1.0.0
Requires-Dist: websockets>=13.1
Requires-Dist: yt-dlp>=2024.11.04
Provides-Extra: full
Requires-Dist: brotli>=1.1.0; implementation_name == "cpython" and extra == "full"
Requires-Dist: brotlicffi>=1.1.0; implementation_name != "cpython" and extra == "full"
Requires-Dist: mutagen>=1.47.0; extra == "full"
Requires-Dist: pycryptodomex>=3.21.0; extra == "full"
Requires-Dist: pyyaml>=6.0.2; extra == "full"
Requires-Dist: toml>=0.10.2; python_version <= "3.10" and extra == "full"
Provides-Extra: build
Requires-Dist: build>=1.2.2; extra == "build"
Requires-Dist: pip>=24.3; extra == "build"
Requires-Dist: pyinstaller>=6.10.0; extra == "build"
Requires-Dist: setuptools>=75.6.0; extra == "build"
Requires-Dist: wheel>=0.45.0; extra == "build"
Provides-Extra: dev
Requires-Dist: pre-commit>=4.0.0; extra == "dev"
Requires-Dist: ruff>=0.9.0; extra == "dev"
Dynamic: license-file
